tapflow/__init__.py
tapflow/version.py
tapflow/cli/__init__.py
tapflow/cli/cli.py
tapflow/cli/tap.py
tapflow/lib/__init__.py
tapflow/lib/cache.py
tapflow/lib/check.py
tapflow/lib/graph.py
tapflow/lib/help_decorator.py
tapflow/lib/login.py
tapflow/lib/op_object.py
tapflow/lib/request.py
tapflow/lib/advanced/__init__.py
tapflow/lib/advanced/cdc_log_cache.py
tapflow/lib/advanced/heartbeat_task.py
tapflow/lib/advanced/live_cache.py
tapflow/lib/backend_apis/__init__.py
tapflow/lib/backend_apis/apiServers.py
tapflow/lib/backend_apis/common.py
tapflow/lib/backend_apis/connections.py
tapflow/lib/backend_apis/dataSource.py
tapflow/lib/backend_apis/dataVerify.py
tapflow/lib/backend_apis/metadataInstance.py
tapflow/lib/backend_apis/task.py
tapflow/lib/commands/__init__.py
tapflow/lib/commands/api_command.py
tapflow/lib/commands/op_object_command.py
tapflow/lib/commands/show_command.py
tapflow/lib/configuration/__init__.py
tapflow/lib/configuration/config.py
tapflow/lib/connections/__init__.py
tapflow/lib/connections/connection.py
tapflow/lib/connections/connection_list.py
tapflow/lib/data_pipeline/__init__.py
tapflow/lib/data_pipeline/base_node.py
tapflow/lib/data_pipeline/base_obj.py
tapflow/lib/data_pipeline/dag.py
tapflow/lib/data_pipeline/data_source.py
tapflow/lib/data_pipeline/job.py
tapflow/lib/data_pipeline/pipeline.py
tapflow/lib/data_pipeline/nodes/__init__.py
tapflow/lib/data_pipeline/nodes/column_filter.py
tapflow/lib/data_pipeline/nodes/field_add_del.py
tapflow/lib/data_pipeline/nodes/field_calculate.py
tapflow/lib/data_pipeline/nodes/field_rename.py
tapflow/lib/data_pipeline/nodes/filter.py
tapflow/lib/data_pipeline/nodes/js.py
tapflow/lib/data_pipeline/nodes/merge.py
tapflow/lib/data_pipeline/nodes/py.py
tapflow/lib/data_pipeline/nodes/python.py
tapflow/lib/data_pipeline/nodes/rename.py
tapflow/lib/data_pipeline/nodes/rename_table.py
tapflow/lib/data_pipeline/nodes/row_filter.py
tapflow/lib/data_pipeline/nodes/sink.py
tapflow/lib/data_pipeline/nodes/source.py
tapflow-0.2.81.dist-info/METADATA
tapflow-0.2.81.dist-info/WHEEL
tapflow-0.2.81.dist-info/entry_points.txt
tapflow-0.2.81.dist-info/top_level.txt
tapflow-0.2.81.dist-info/RECORD
